findfile/__init__.py
findfile/file_manager.py
findfile/find.py
findfile-2.1.1.post1.dist-info/licenses/LICENSE
findfile-2.1.1.post1.dist-info/METADATA
findfile-2.1.1.post1.dist-info/WHEEL
findfile-2.1.1.post1.dist-info/top_level.txt
findfile-2.1.1.post1.dist-info/RECORD
