Metadata-Version: 2.4
Name: findfile
Version: 2.1.1.post1
Summary: This package provides the function to search target file(s)/dir(s) using keyword, alleviating the possibility of failure to find files by specifying relative/absolute path
Home-page: https://github.com/yangheng95/findfile
Author: Yang Heng
Author-email: yangheng@m.scnu.edu.cn
License: MIT
Requires-Python: >=3.6
License-File: LICENSE
Requires-Dist: termcolor
Dynamic: author
Dynamic: author-email
Dynamic: home-page
Dynamic: license
Dynamic: license-file
Dynamic: requires-dist
Dynamic: requires-python
Dynamic: summary
